<?xml version='1.0' encoding='UTF-8'?>
<tv source_info_url="https://www.tvguide.co.uk/">
  <channel id="1013.tvguide.co.uk">
    <display-name lang="en">Blaze</display-name>
  </channel>
  <channel id="1014.tvguide.co.uk">
    <display-name lang="en">Quest Red</display-name>
  </channel>
  <channel id="1207.tvguide.co.uk">
    <display-name lang="en">Kerrang!</display-name>
  </channel>
  <channel id="1230.tvguide.co.uk">
    <display-name lang="en">Quest HD</display-name>
  </channel>
  <channel id="178.tvguide.co.uk">
    <display-name lang="en">STV Central</display-name>
  </channel>
  <channel id="182.tvguide.co.uk">
    <display-name lang="en">Kiss TV</display-name>
  </channel>
  <channel id="185.tvguide.co.uk">
    <display-name lang="en">Magic</display-name>
  </channel>
  <channel id="257.tvguide.co.uk">
    <display-name lang="en">Sky News</display-name>
  </channel>
  <channel id="267.tvguide.co.uk">
    <display-name lang="en">Box Hits</display-name>
  </channel>
  <channel id="279.tvguide.co.uk">
    <display-name lang="en">The Box</display-name>
  </channel>
  <channel id="320.tvguide.co.uk">
    <display-name lang="en">Yesterday</display-name>
  </channel>
  <channel id="432.tvguide.co.uk">
    <display-name lang="en">Dave</display-name>
  </channel>
  <channel id="871.tvguide.co.uk">
    <display-name lang="en">Drama</display-name>
  </channel>
  <programme channel="1013.tvguide.co.uk" start="20200303233000" stop="20200304000000">
    <title lang="en">Storage Wars</title>
    <sub-title lang="en">What Cowboy Dreams May Come</sub-title>
    <desc lang="en">The buyers head to auctions in Santa Ana, and once back on familiar turf, Dave Hester makes the others fight for a decent locker.</desc>
    <category lang="en">News</category>
    <category lang="en">Current Affairs</category>
    <episode-num system="xmltv_ns">7.9/20.</episode-num>
    <star-rating>
      <value>6.5/10</value>
    </star-rating>
  </programme>
  <programme channel="1013.tvguide.co.uk" start="20200304000000" stop="20200304003000">
    <title lang="en">Auction Hunters</title>
    <sub-title lang="en">Ton's Got a Gun</sub-title>
    <desc lang="en">Ton Jones and Allen Haff try to make a profit by selling a 19th-century Colt Peacemaker pistol, a Depression-era slot machine and a customised mini-bike.</desc>
    <category lang="en">Show</category>
    <category lang="en">Game Show</category>
    <episode-num system="xmltv_ns">0.2/8.</episode-num>
    <star-rating>
      <value>8.2/10</value>
    </star-rating>
  </programme>
  <programme channel="1013.tvguide.co.uk" start="20200304003000" stop="20200304010000">
    <title lang="en">Auction Hunters</title>
    <sub-title lang="en">Strat'd for Cash</sub-title>
    <desc lang="en">The traders discover a valuable 1970s Fender Stratocaster guitar and a rare Schwinn bicycle from the 1930s.</desc>
    <category lang="en">Show</category>
    <category lang="en">Game Show</category>
    <episode-num system="xmltv_ns">0.3/8.</episode-num>
    <star-rating>
      <value>8.2/10</value>
    </star-rating>
  </programme>
  <programme channel="1013.tvguide.co.uk" start="20200304010000" stop="20200304013000">
    <title lang="en">Storage Wars: Texas</title>
    <sub-title lang="en">A Fistful of Auctions</sub-title>
    <desc lang="en">The bidders consider the benefits and drawbacks of two very different neighbourhoods, and Lesa displays her ruthless side while dealing with a young buyer.</desc>
    <category lang="en">News</category>
    <category lang="en">Current Affairs</category>
    <episode-num system="xmltv_ns">0.6/16.</episode-num>
    <star-rating>
      <value>5.3/10</value>
    </star-rating>
  </programme>
  <programme channel="1013.tvguide.co.uk" start="20200304013000" stop="20200304020000">
    <title lang="en">Storage Wars: Texas</title>
    <sub-title lang="en">High Tea Tighty</sub-title>
    <desc lang="en">A piano, a tea set and some expensive furniture are among the finds up for grabs when the buyers go to Lewisville, Texas.</desc>
    <category lang="en">News</category>
    <category lang="en">Current Affairs</category>
    <episode-num system="xmltv_ns">0.7/16.</episode-num>
    <star-rating>
      <value>5.3/10</value>
    </star-rating>
  </programme>
  <programme channel="1013.tvguide.co.uk" start="20200304020000" stop="20200304023000">
    <title lang="en">American Restoration</title>
    <sub-title lang="en">Gone to Pieces</sub-title>
    <desc lang="en">Big Mike brings a 1960s motorcycle into the shop, and the guys search for rare parts to restore it, while Rick works on an arcade game.</desc>
    <category lang="en">Education</category>
    <category lang="en">Science</category>
    <category lang="en">Factual</category>
    <episode-num system="xmltv_ns">4.16/21.</episode-num>
    <star-rating>
      <value>7/10</value>
    </star-rating>
  </programme>
  <programme channel="1013.tvguide.co.uk" start="20200304023000" stop="20200304030000">
    <title lang="en">American Restoration</title>
    <sub-title lang="en">Star Wreck</sub-title>
    <desc lang="en">The team turns a petrol pump into a beer cooler and restore a sign from a 1970s fast food restaurant.</desc>
    <category lang="en">Education</category>
    <category lang="en">Science</category>
    <category lang="en">Factual</category>
    <episode-num system="xmltv_ns">4.17/21.</episode-num>
    <star-rating>
      <value>7/10</value>
    </star-rating>
  </programme>
  <programme channel="1013.tvguide.co.uk" start="20200304030000" stop="20200304040000">
    <title lang="en">Swamp People</title>
    <sub-title lang="en">Divide to Conquer</sub-title>
    <desc lang="en">Joe seems to be having a successful day on the swamp, until he suffers a serious injury, that jeopardises his entire season.</desc>
    <category lang="en">Education</category>
    <category lang="en">Science</category>
    <category lang="en">Factual</category>
    <episode-num system="xmltv_ns">2.2/22.</episode-num>
    <star-rating>
      <value>7.7/10</value>
    </star-rating>
  </programme>
  <programme channel="1013.tvguide.co.uk" start="20200304040000" stop="20200304043000">
    <title lang="en">Ernie the Wildman</title>
    <sub-title lang="en">Fort Rattlesnake</sub-title>
    <desc lang="en">A raccoon is spotted at an old trading post by Ernie Brown Jr, but he must remove the creature without harming the historic structure.</desc>
    <category lang="en">Education</category>
    <category lang="en">Science</category>
    <category lang="en">Factual</category>
    <episode-num system="xmltv_ns">0.5/29.</episode-num>
    <star-rating>
      <value>8.2/10</value>
    </star-rating>
  </programme>
  <programme channel="1013.tvguide.co.uk" start="20200304043000" stop="20200304050000">
    <title lang="en">Ernie the Wildman</title>
    <sub-title lang="en">Turtle Boot Camp</sub-title>
    <desc lang="en">Ernie Brown Jr tries to catch a mysterious predator that is taking a farmer's hens from his chicken coop.</desc>
    <category lang="en">Education</category>
    <category lang="en">Science</category>
    <category lang="en">Factual</category>
    <episode-num system="xmltv_ns">0.6/29.</episode-num>
    <star-rating>
      <value>8.2/10</value>
    </star-rating>
  </programme>
  <programme channel="1013.tvguide.co.uk" start="20200304050000" stop="20200304053000">
    <title lang="en">Pawn Stars</title>
    <sub-title lang="en">Bikes and Blades</sub-title>
    <desc lang="en">Corey considers buying a flawed 1996 Harley Road King motorcycle, and the team examines knives dating back to the Second World War.</desc>
    <category lang="en">News</category>
    <category lang="en">Current Affairs</category>
    <episode-num system="xmltv_ns">1.8/14.</episode-num>
    <star-rating>
      <value>7.1/10</value>
    </star-rating>
  </programme>
  <programme channel="1013.tvguide.co.uk" start="20200304053000" stop="20200304060000">
    <title lang="en">Pawn Stars</title>
    <sub-title lang="en">Rick's Bad Day</sub-title>
    <desc lang="en">The team examines a German bayonet from the Second World War, and Richard takes a gamble with a 1930s slot machine.</desc>
    <category lang="en">News</category>
    <category lang="en">Current Affairs</category>
    <episode-num system="xmltv_ns">1.9/14.</episode-num>
    <star-rating>
      <value>7.1/10</value>
    </star-rating>
  </programme>
  <programme channel="432.tvguide.co.uk" start="20200303230000" stop="20200304000000">
    <title lang="en">Dara O Briain's Go 8 Bit</title>
    <sub-title lang="en">Gregg Wallace v Jodie Kidd</sub-title>
    <desc lang="en">Guests Gregg Wallace and Jodie Kidd play a series of video games, including Spy Hunter, Total War: Rome II and Battlefield 1.</desc>
    <category lang="en">Show</category>
    <category lang="en">Game Show</category>
    <episode-num system="xmltv_ns">2.0/10.</episode-num>
    <subtitles type="teletext" />
    <star-rating>
      <value>7.2/10</value>
    </star-rating>
  </programme>
  <programme channel="432.tvguide.co.uk" start="20200304000000" stop="20200304010000">
    <title lang="en">Taskmaster</title>
    <sub-title lang="en">Twelve Blush Majesty Two</sub-title>
    <desc lang="en">Rhod Gilbert force-feeds Alex Horne a jug of mocha, Kerry Godliman hits a cricket ball with a croquet mallet, and Phil Wang makes a really strange noise.</desc>
    <category lang="en">Show</category>
    <category lang="en">Game Show</category>
    <episode-num system="xmltv_ns">6.2/10.</episode-num>
    <subtitles type="teletext" />
    <star-rating>
      <value>7.2/10</value>
    </star-rating>
  </programme>
  <programme channel="432.tvguide.co.uk" start="20200304010000" stop="20200304021500">
    <title lang="en">Have I Got a Bit More News for You</title>
    <sub-title lang="en">Have I Got a Bit More Old News for You</sub-title>
    <desc lang="en">Extended edition. Comedian, writer and actress Katherine Ryan guest hosts the satirical quiz, with stand-up Joe Wilkinson and broadcaster and writer Gyles Brandreth joining regular team captains Paul Merton and Ian Hislop to poke fun at the week's news.</desc>
    <category lang="en">Comedy</category>
    <episode-num system="xmltv_ns">50.7/9.</episode-num>
    <subtitles type="teletext" />
    <star-rating>
      <value>6.7/10</value>
    </star-rating>
  </programme>
  <programme channel="432.tvguide.co.uk" start="20200304021500" stop="20200304030000">
    <title lang="en">Jon Richardson: Ultimate Worrier</title>
    <sub-title lang="en">Food</sub-title>
    <desc lang="en">This time, Jon is joined by Victoria Coren-Mitchell and Rob Beckett as they attempt to analyse and assess the things that worry them the most about the food that we eat.</desc>
    <category lang="en">Comedy</category>
    <episode-num system="xmltv_ns">0.2/8.</episode-num>
    <subtitles type="teletext" />
    <star-rating>
      <value>6.4/10</value>
    </star-rating>
  </programme>
  <programme channel="432.tvguide.co.uk" start="20200304030000" stop="20200304033500">
    <title lang="en">Zapped</title>
    <sub-title lang="en">Popcorn</sub-title>
    <desc lang="en">Brian introduces popcorn to Munty, Barbara dreams of becoming one of the famous Munty Clack Dancers and Howell makes a truth potion for Slasher Morgan - with disastrous results.</desc>
    <category lang="en">Sitcom</category>
    <episode-num system="xmltv_ns">2.2/6.</episode-num>
    <subtitles type="teletext" />
    <star-rating>
      <value>7.8/10</value>
    </star-rating>
  </programme>
  <programme channel="432.tvguide.co.uk" start="20200304033500" stop="20200304040000">
    <title lang="en">The Indestructibles</title>
    <sub-title lang="en">Drift Off to Sleep</sub-title>
    <desc lang="en">Adventurers Tim and Gendle are given an epic downhill location and three days to pull off a spectacular festival of drift.</desc>
    <category lang="en">News</category>
    <category lang="en">Current Affairs</category>
    <episode-num system="xmltv_ns">0.8/12.</episode-num>
    <star-rating>
      <value>7.9/10</value>
    </star-rating>
  </programme>
  <programme channel="432.tvguide.co.uk" start="20200304040000" stop="20200304060000">
    <title lang="en">Teleshopping</title>
    <desc lang="en">A chance to buy goods from the comfort of home.</desc>
    <category lang="en">Leisure</category>
    <category lang="en">Hobbies</category>
    <star-rating>
      <value>2.6/10</value>
    </star-rating>
  </programme>
  <programme channel="320.tvguide.co.uk" start="20200303235500" stop="20200304005500">
    <title lang="en">Underground Worlds</title>
    <sub-title lang="en">Jersey War Tunnels</sub-title>
    <desc lang="en">The underground bases built by the German army during the occupation of Jersey, and a group of more than 20 underground cities in Turkey, one of which dates back to 800BC.</desc>
    <category lang="en">News</category>
    <category lang="en">Current Affairs</category>
    <episode-num system="xmltv_ns">0.6/10.</episode-num>
    <subtitles type="teletext" />
    <star-rating>
      <value>6.8/10</value>
    </star-rating>
  </programme>
  <programme channel="320.tvguide.co.uk" start="20200304005500" stop="20200304015500">
    <title lang="en">Nazi Victory: The Post-War Plan</title>
    <sub-title lang="en">America</sub-title>
    <desc lang="en">Hitler's plans to invade the US using battleships, long-range bombers and secret infiltrators. Plus, a look at support for the Nazi movement in America during the 1940s.</desc>
    <category lang="en">News</category>
    <category lang="en">Current Affairs</category>
    <episode-num system="xmltv_ns">0.2/6.</episode-num>
    <subtitles type="teletext" />
    <star-rating>
      <value>3.1/10</value>
    </star-rating>
  </programme>
  <programme channel="320.tvguide.co.uk" start="20200304015500" stop="20200304030000">
    <title lang="en">Ronnie Kray and the Pervert Peer</title>
    <sub-title lang="en">(Audio Described)</sub-title>
    <desc lang="en">Fifty years ago, the Kray twins rose from small-time racketeers to head the most powerful criminal organisation London had ever seen. This documentary about the affinity between the upper echelons of society and the criminal underclass reveals how they built their empire on fear, violence and extortion - as well as Ronnie's alleged homosexual relationship with a prominent Tory peer.</desc>
    <category lang="en">News</category>
    <category lang="en">Current Affairs</category>
    <subtitles type="teletext" />
  </programme>
  <programme channel="320.tvguide.co.uk" start="20200304030000" stop="20200304060000">
    <title lang="en">Teleshopping</title>
    <desc lang="en">A chance to buy goods from the comfort of home.</desc>
    <category lang="en">Leisure</category>
    <category lang="en">Hobbies</category>
    <star-rating>
      <value>2.6/10</value>
    </star-rating>
  </programme>
  <programme channel="871.tvguide.co.uk" start="20200303231500" stop="20200304015500">
    <title lang="en">Waking the Dead</title>
    <sub-title lang="en">Life Sentence</sub-title>
    <desc lang="en">Feature-length episode. When the only living victim of a jailed serial killer starts being harassed by a stalker, Boyd is given the chance to prove his theory that the murderer had a partner who is still on the loose. Starring Trevor Eve and Sue Johnston.</desc>
    <credits>
      <actor>Trevor Eve</actor>
      <actor>Sue Johnston</actor>
    </credits>
    <category lang="en">Detective</category>
    <category lang="en">Thriller</category>
    <episode-num system="xmltv_ns">1.0/4.</episode-num>
    <star-rating>
      <value>8.1/10</value>
    </star-rating>
  </programme>
  <programme channel="871.tvguide.co.uk" start="20200304015500" stop="20200304024500">
    <title lang="en">The Bill</title>
    <sub-title lang="en">Taking a Stand</sub-title>
    <desc lang="en">Leela urges her hospitalised father to make a statement about his attackers, and is warned her own life is in danger - which only increases her determination to pursue the case to the bitter end. Jo goes on the trail of a violent pimp and offers a local prostitute the chance to become a police informant, while Gabriel shows his compassionate side by protecting a little girl he suspects is being abused. Honey brushes aside Yvonne's concerns about her engagement to Scott, putting it down to jealousy - unaware of Yvonne's budding romance with A&amp;E nurse Nick.</desc>
    <category lang="en">Police</category>
    <category lang="en">Crime Drama</category>
    <episode-num system="xmltv_ns">20.18/103.</episode-num>
    <subtitles type="teletext" />
    <star-rating>
      <value>5.6/10</value>
    </star-rating>
  </programme>
  <programme channel="871.tvguide.co.uk" start="20200304024500" stop="20200304040000">
    <title lang="en">London's Burning</title>
    <desc lang="en">Bayleaf grows more concerned about his daughter's whereabouts and hires a private investigator to recover her. Meanwhile, the team are called out to help an elderly man.</desc>
    <category lang="en">General</category>
    <episode-num system="xmltv_ns">4.6/10.</episode-num>
    <subtitles type="teletext" />
    <star-rating>
      <value>4.6/10</value>
    </star-rating>
  </programme>
  <programme channel="871.tvguide.co.uk" start="20200304040000" stop="20200304060000">
    <title lang="en">Teleshopping</title>
    <desc lang="en">A chance to buy goods from the comfort of home.</desc>
    <category lang="en">Leisure</category>
    <category lang="en">Hobbies</category>
    <star-rating>
      <value>2.6/10</value>
    </star-rating>
  </programme>
  <programme channel="257.tvguide.co.uk" start="20200303233000" stop="20200304000000">
    <title lang="en">Press Preview</title>
    <sub-title lang="en">04/03/2020 - 2</sub-title>
    <desc lang="en">A preview of the stories appearing in tomorrow's national newspapers.</desc>
    <category lang="en">Arts</category>
    <category lang="en">Culture (without music)</category>
    <star-rating>
      <value>6.4/10</value>
    </star-rating>
  </programme>
  <programme channel="257.tvguide.co.uk" start="20200304000000" stop="20200304003000">
    <title lang="en">Sky Midnight News</title>
    <desc lang="en">Update on the day's headlines, plus a weather report.</desc>
    <category lang="en">News</category>
    <category lang="en">Current Affairs</category>
    <star-rating>
      <value>2.8/10</value>
    </star-rating>
  </programme>
  <programme channel="257.tvguide.co.uk" start="20200304003000" stop="20200304010000">
    <title lang="en">Press Preview</title>
    <sub-title lang="en">04/03/2020 - 2</sub-title>
    <desc lang="en">A preview of the stories appearing in tomorrow's national newspapers.</desc>
    <category lang="en">Arts</category>
    <category lang="en">Culture (without music)</category>
    <star-rating>
      <value>6.4/10</value>
    </star-rating>
  </programme>
  <programme channel="257.tvguide.co.uk" start="20200304010000" stop="20200304013000">
    <title lang="en">Sky News on the Hour</title>
    <desc lang="en">Review of the latest international news, with sport, weather and financial updates.</desc>
    <category lang="en">News</category>
    <category lang="en">Current Affairs</category>
    <star-rating>
      <value>1/10</value>
    </star-rating>
  </programme>
  <programme channel="257.tvguide.co.uk" start="20200304013000" stop="20200304020000">
    <title lang="en">Ian King Live</title>
    <sub-title lang="en">04/03/2020</sub-title>
    <desc lang="en">All the day's business news live from Sky's City of London studio, with Ian King.</desc>
    <category lang="en">Social</category>
    <category lang="en">Political</category>
    <category lang="en">Economics</category>
    <star-rating>
      <value>6/10</value>
    </star-rating>
  </programme>
  <programme channel="257.tvguide.co.uk" start="20200304020000" stop="20200304023000">
    <title lang="en">Sky News on the Hour</title>
    <desc lang="en">Review of the latest international news, with sport, weather and financial updates.</desc>
    <category lang="en">News</category>
    <category lang="en">Current Affairs</category>
    <star-rating>
      <value>1/10</value>
    </star-rating>
  </programme>
  <programme channel="257.tvguide.co.uk" start="20200304023000" stop="20200304030000">
    <title lang="en">Sky News on the Hour</title>
    <desc lang="en">Review of the latest international news, with sport, weather and financial updates.</desc>
    <category lang="en">News</category>
    <category lang="en">Current Affairs</category>
    <star-rating>
      <value>1/10</value>
    </star-rating>
  </programme>
  <programme channel="257.tvguide.co.uk" start="20200304030000" stop="20200304040000">
    <title lang="en">Sky News</title>
    <desc lang="en">A summary of the latest news headlines.</desc>
    <category lang="en">News</category>
    <category lang="en">Current Affairs</category>
    <star-rating>
      <value>6.3/10</value>
    </star-rating>
  </programme>
  <programme channel="257.tvguide.co.uk" start="20200304040000" stop="20200304050000">
    <title lang="en">Sky News</title>
    <desc lang="en">A summary of the latest news headlines.</desc>
    <category lang="en">News</category>
    <category lang="en">Current Affairs</category>
    <star-rating>
      <value>6.3/10</value>
    </star-rating>
  </programme>
  <programme channel="257.tvguide.co.uk" start="20200304050000" stop="20200304053000">
    <title lang="en">Sky News</title>
    <desc lang="en">A summary of the latest news headlines.</desc>
    <category lang="en">News</category>
    <category lang="en">Current Affairs</category>
    <star-rating>
      <value>6.3/10</value>
    </star-rating>
  </programme>
  <programme channel="257.tvguide.co.uk" start="20200304053000" stop="20200304060000">
    <title lang="en">Press Preview</title>
    <sub-title lang="en">04/03/2020 - 2</sub-title>
    <desc lang="en">A preview of the stories appearing in tomorrow's national newspapers.</desc>
    <category lang="en">Arts</category>
    <category lang="en">Culture (without music)</category>
    <star-rating>
      <value>6.4/10</value>
    </star-rating>
  </programme>
  <programme channel="178.tvguide.co.uk" start="20200303230500" stop="20200304000500">
    <title lang="en">Peston</title>
    <desc lang="en">Political magazine show presented by Robert Peston, featuring major interviews with MPs, topical guests and cultural figures. Including updates from social media taking in perspectives from viewers, experts and key players throughout the programme.</desc>
    <category lang="en">Social</category>
    <category lang="en">Political</category>
    <category lang="en">Economics</category>
    <episode-num system="xmltv_ns">2019.6.</episode-num>
    <subtitles type="teletext" />
    <star-rating>
      <value>2.3/10</value>
    </star-rating>
  </programme>
  <programme channel="178.tvguide.co.uk" start="20200304000500" stop="20200304010000">
    <title lang="en">The Home Game</title>
    <desc lang="en">A couple in Surrey hope their home will benefit from a lavish renovation, a man in Wales attempts to build an extension for less than £8,000, and a Shoreham property receives a garden makeover. Linda Barker presents.</desc>
    <category lang="en">Show</category>
    <category lang="en">Game Show</category>
    <episode-num system="xmltv_ns">0.7/10.</episode-num>
    <previously-shown />
    <subtitles type="teletext" />
    <star-rating>
      <value>4/10</value>
    </star-rating>
  </programme>
  <programme channel="178.tvguide.co.uk" start="20200304010000" stop="20200304050500">
    <title lang="en">ITV Nightscreen</title>
    <desc lang="en">Text-based information service.</desc>
    <category lang="en">Education</category>
    <category lang="en">Science</category>
    <category lang="en">Factual</category>
    <star-rating>
      <value>3.1/10</value>
    </star-rating>
  </programme>
  <programme channel="178.tvguide.co.uk" start="20200304050500" stop="20200304060000">
    <title lang="en">Judge Rinder</title>
    <sub-title lang="en">(Sign Language)</sub-title>
    <desc lang="en">Cameras follow criminal barrister Robert Rinder as he takes on real-life cases in a studio courtroom.</desc>
    <category lang="en">Education</category>
    <category lang="en">Science</category>
    <category lang="en">Factual</category>
    <episode-num system="xmltv_ns">6.79.</episode-num>
    <previously-shown />
    <subtitles type="teletext" />
    <star-rating>
      <value>1.9/10</value>
    </star-rating>
  </programme>
  <programme channel="185.tvguide.co.uk" start="20200303230000" stop="20200304000000">
    <title lang="en">90s vs 00s: Chilled Anthems</title>
    <desc lang="en">Sit back, relax and enjoy the most chilled tunes the nineties and noughties had to offer.</desc>
    <category lang="en">General</category>
  </programme>
  <programme channel="185.tvguide.co.uk" start="20200304000000" stop="20200304060000">
    <title lang="en">Late Night Magic</title>
    <desc lang="en">We're taking you all the way through the night with soem of the best tracks of all time.</desc>
    <category lang="en">General</category>
  </programme>
  <programme channel="182.tvguide.co.uk" start="20200303230000" stop="20200304010000">
    <title lang="en">Kisstory: Old Skool &amp; Anthems</title>
    <desc lang="en">It's time to go back in time with KISSTORY! The biggest old skool anthems ever from your favourite artists.</desc>
    <category lang="en">General</category>
  </programme>
  <programme channel="182.tvguide.co.uk" start="20200304010000" stop="20200304060000">
    <title lang="en">Up All Night! Kiss Beats</title>
    <desc lang="en">Let the world sleep! But here at Kiss we are still up, still delivering the finest beats for your nocturnal jam.</desc>
    <category lang="en">General</category>
  </programme>
  <programme channel="279.tvguide.co.uk" start="20200303230000" stop="20200304060000">
    <title lang="en">Chart Hits &amp; New Vids</title>
    <desc lang="en">We've got all the hits that are storming the charts right now, along with some brand new releases from your favourite and new artists.</desc>
    <category lang="en">General</category>
    <star-rating>
      <value>7/10</value>
    </star-rating>
  </programme>
  <programme channel="267.tvguide.co.uk" start="20200303233000" stop="20200304060000">
    <title lang="en">Hit After Hit</title>
    <desc lang="en">Nothing but the biggest hits by your favourite stars back to back.</desc>
    <category lang="en">General</category>
    <star-rating>
      <value>9/10</value>
    </star-rating>
  </programme>
  <programme channel="1014.tvguide.co.uk" start="20200303230000" stop="20200304000000">
    <title lang="en">FBI Case Files</title>
    <sub-title lang="en">Taken by Force</sub-title>
    <desc lang="en">Texas police join an FBI investigation into the kidnapping of a 16-year-old girl by a drug-trafficking gang.</desc>
    <category lang="en">News</category>
    <category lang="en">Current Affairs</category>
    <episode-num system="xmltv_ns">3.7/13.</episode-num>
    <star-rating>
      <value>7.9/10</value>
    </star-rating>
  </programme>
  <programme channel="1014.tvguide.co.uk" start="20200304000000" stop="20200304010000">
    <title lang="en">Forensic Detectives</title>
    <sub-title lang="en">Misplaced Loyalty</sub-title>
    <desc lang="en">Firefighters discover an unidentified charred body when they are called to the scene of a house fire in the middle of the night.</desc>
    <category lang="en">News</category>
    <category lang="en">Current Affairs</category>
    <episode-num system="xmltv_ns">8.4/18.</episode-num>
    <star-rating>
      <value>7.2/10</value>
    </star-rating>
  </programme>
  <programme channel="1014.tvguide.co.uk" start="20200304010000" stop="20200304020000">
    <title lang="en">Crime Stories</title>
    <sub-title lang="en">Clarence Pallet</sub-title>
    <desc lang="en">How the family of Clarence Pallet sought justice after her killer disappeared after being released from prison early in 1971..</desc>
    <category lang="en">Education</category>
    <category lang="en">Science</category>
    <category lang="en">Factual</category>
    <episode-num system="xmltv_ns">7.5/9.</episode-num>
    <star-rating>
      <value>5.3/10</value>
    </star-rating>
  </programme>
  <programme channel="1014.tvguide.co.uk" start="20200304020000" stop="20200304030000">
    <title lang="en">Murder Comes to Town</title>
    <sub-title lang="en">The Dangers of Success</sub-title>
    <desc lang="en">The fatal shooting of Terri Ann McCoy on her family home's landing, by a lookout guarding fellow robbers who had invaded the building to steal jewellery in November 2009.</desc>
    <category lang="en">Education</category>
    <category lang="en">Science</category>
    <category lang="en">Factual</category>
    <episode-num system="xmltv_ns">4.4/10.</episode-num>
    <star-rating>
      <value>7/10</value>
    </star-rating>
  </programme>
  <programme channel="1014.tvguide.co.uk" start="20200304030000" stop="20200304035000">
    <title lang="en">FBI Files</title>
    <sub-title lang="en">Inside the Bureau</sub-title>
    <desc lang="en">Officers reveal a sophisticated burglary with estimated losses of £8million when they investigate why a bank manager is unable to open his vault.</desc>
    <category lang="en">News</category>
    <category lang="en">Current Affairs</category>
    <episode-num system="xmltv_ns">5.14/22.</episode-num>
    <star-rating>
      <value>7.3/10</value>
    </star-rating>
  </programme>
  <programme channel="1014.tvguide.co.uk" start="20200304035000" stop="20200304044000">
    <title lang="en">Animal Cops Phoenix</title>
    <sub-title lang="en">Playful Pit Puppy</sub-title>
    <desc lang="en">The members of the Emergency Animal Medical Technician team in Phoenix have their work cut out as they rescue and care for animals in trouble.</desc>
    <category lang="en">Education</category>
    <category lang="en">Science</category>
    <category lang="en">Factual</category>
    <episode-num system="xmltv_ns">1.10/15.</episode-num>
    <star-rating>
      <value>4.3/10</value>
    </star-rating>
  </programme>
  <programme channel="1014.tvguide.co.uk" start="20200304044000" stop="20200304053000">
    <title lang="en">Bondi Vet</title>
    <desc lang="en">Sydney veterinary surgeon Dr Chris Brown feels the pressure when he comes to the aid of a distressed Sumatran tiger with a tooth problem.</desc>
    <category lang="en">Education</category>
    <category lang="en">Science</category>
    <category lang="en">Factual</category>
    <episode-num system="xmltv_ns">5.4/15.</episode-num>
    <star-rating>
      <value>7.1/10</value>
    </star-rating>
  </programme>
  <programme channel="1014.tvguide.co.uk" start="20200304053000" stop="20200304060000">
    <title lang="en">Say Yes to the Dress</title>
    <sub-title lang="en">Indecisive Brides</sub-title>
    <desc lang="en">A woman returns a ballroom-style dress so that she can buy one that better suits her edgy tastes.</desc>
    <category lang="en">News</category>
    <category lang="en">Current Affairs</category>
    <episode-num system="xmltv_ns">2.16/18.</episode-num>
    <star-rating>
      <value>5.3/10</value>
    </star-rating>
  </programme>
</tv>
